pj_scraper/__init__.py
pj_scraper/__main__.py
pj_scraper/_version.py
pj_scraper/cli.py
pj_scraper/scraper.py
pj_scraper/tests/__init__.py
pj_scraper/tests/test_scraper.py
pj_scraper-0.0.4.dist-info/AUTHORS.rst
pj_scraper-0.0.4.dist-info/LICENSE
pj_scraper-0.0.4.dist-info/METADATA
pj_scraper-0.0.4.dist-info/WHEEL
pj_scraper-0.0.4.dist-info/entry_points.txt
pj_scraper-0.0.4.dist-info/top_level.txt
pj_scraper-0.0.4.dist-info/RECORD
